gvar/__init__.pxd
gvar/__init__.py
gvar/_bufferdict.cpython-312-x86_64-linux-musl.so
gvar/_bufferdict.pyx
gvar/_gvarcore.cpython-312-x86_64-linux-musl.so
gvar/_gvarcore.pxd
gvar/_gvarcore.pyx
gvar/_svec_smat.cpython-312-x86_64-linux-musl.so
gvar/_svec_smat.pxd
gvar/_svec_smat.pyx
gvar/_utilities.cpython-312-x86_64-linux-musl.so
gvar/_utilities.pyx
gvar/cspline.py
gvar/dataset.cpython-312-x86_64-linux-musl.so
gvar/dataset.pyx
gvar/linalg.py
gvar/ode.py
gvar/pade.py
gvar/powerseries.py
gvar/root.py
gvar-13.1.9.dist-info/METADATA
gvar-13.1.9.dist-info/WHEEL
gvar-13.1.9.dist-info/top_level.txt
gvar-13.1.9.dist-info/RECORD
gvar-13.1.9.dist-info/licenses/LICENSE.txt
