Metadata-Version: 2.4
Name: gvar
Version: 13.1.9
Summary: Utilities for manipulating correlated Gaussian random variables.
Author-email: "G. Peter Lepage" <g.p.lepage@cornell.edu>
License-Expression: GPL-3.0+
Project-URL: Homepage, https://github.com/gplepage/gvar
Project-URL: Issues, https://github.com/gplepage/gvar/issues
Classifier: Programming Language :: Python :: 3
Classifier: Operating System :: OS Independent
Requires-Python: >=3.11
License-File: LICENSE.txt
Requires-Dist: numpy>=1.24
Requires-Dist: scipy>=1.11
Dynamic: license-file
